dquota/__init__.py
dquota/providers/__init__.py
dquota/providers/redis/__init__.py
dquota/providers/stdout/__init__.py
dquota-0.4.dist-info/DESCRIPTION.rst
dquota-0.4.dist-info/METADATA
dquota-0.4.dist-info/RECORD
dquota-0.4.dist-info/WHEEL
dquota-0.4.dist-info/metadata.json
dquota-0.4.dist-info/top_level.txt
