Metadata-Version: 2.0
Name: dquota
Version: 0.4
Summary: Handle quota notifications using generic netlink
Home-page: https://github.com/ton31337/dquot-python
Author: Donatas Abraitis
Author-email: donatas.abraitis@gmail.com
License: UNKNOWN
Platform: UNKNOWN
Requires-Dist: pika
Requires-Dist: redis
